MultiBottle-0.1.3.dist-info/DESCRIPTION.rst
MultiBottle-0.1.3.dist-info/METADATA
MultiBottle-0.1.3.dist-info/RECORD
MultiBottle-0.1.3.dist-info/WHEEL
MultiBottle-0.1.3.dist-info/entry_points.txt
MultiBottle-0.1.3.dist-info/metadata.json
MultiBottle-0.1.3.dist-info/top_level.txt
multibottle/__init__.py
multibottle/mbextend.py
multibottle/pages.py
multibottle/mako_templates_folder/__init__.py
multibottle/subpages/__init__.py
multibottle/subpages/basicPage.py
multibottle/subpages/fmPage.py
multibottle/subpages/sitePage.py
