Metadata-Version: 2.0
Name: MultiBottle
Version: 0.1.3
Summary: Additional code to work with Bottle web framework to provide mechanisms for multi app support, together with support for a sitemap built together with the routes table and support for database maintenance and secure logins for a basic site. 
Home-page: https://bitbucket.org/objdict/multiBottle
Author: Ian Ogilvy
Author-email: ian.ogilvy@saltminers.biz
License: LGPL
Keywords: database bottle mongodb pymongo view mvc model
Platform: UNKNOWN
Classifier: Development Status :: 4 - Beta
Classifier: Intended Audience :: Developers
Classifier: Topic :: Software Development :: Libraries :: Python Modules
Classifier: Topic :: Utilities
Classifier: License :: OSI Approved :: GNU Library or Lesser General Public License (LGPL)
Classifier: Operating System :: OS Independent
Classifier: Programming Language :: Python :: 3
Classifier: Programming Language :: Python :: 3.2
Classifier: Programming Language :: Python :: 3.3
Classifier: Programming Language :: Python :: 3.4
Classifier: Programming Language :: Python :: 3.5
Classifier: Programming Language :: Python :: 3.6
Requires-Dist: bottle
Requires-Dist: mako
Requires-Dist: objdict
Requires-Dist: pymongo
Requires-Dist: viewmodel
